shotatlogging/__init__.py
shotatlogging/shotatlogging.py
shotatlogging-0.0.2.dist-info/DESCRIPTION.rst
shotatlogging-0.0.2.dist-info/METADATA
shotatlogging-0.0.2.dist-info/RECORD
shotatlogging-0.0.2.dist-info/WHEEL
shotatlogging-0.0.2.dist-info/metadata.json
shotatlogging-0.0.2.dist-info/top_level.txt
tests/__init__.py
tests/test_shotatlogging.py
