Metadata-Version: 2.0
Name: shotatlogging
Version: 0.0.2
Summary: Provide simple way to initialize logging module with default environment
Home-page: https://github.com/starofrainnight/shotatlogging
Author: Hong-She Liang
Author-email: starofrainnight@gmail.com
License: Apache Software License
Keywords: shotatlogging
Platform: UNKNOWN
Classifier: Development Status :: 2 - Pre-Alpha
Classifier: Intended Audience :: Developers
Classifier: License :: OSI Approved :: Apache Software License
Classifier: Natural Language :: English
Classifier: Programming Language :: Python :: 3
Classifier: Programming Language :: Python :: 3.4
Classifier: Programming Language :: Python :: 3.5
Requires-Dist: PyYAML
